xyl_client/__init__.py
xyl_client/client.py
xyl_client.py-0.2.1.dist-info/LICENSE
xyl_client.py-0.2.1.dist-info/METADATA
xyl_client.py-0.2.1.dist-info/WHEEL
xyl_client.py-0.2.1.dist-info/top_level.txt
xyl_client.py-0.2.1.dist-info/RECORD
