Metadata-Version: 2.1
Name: xyl-client.py
Version: 0.2.1
Summary: Client library to interact with the XYL Network
Home-page: https://github.com/debxylen/xyl-client.py
Author: debxylen
Author-email: priyanshudeb3@gmail.com
Classifier: Programming Language :: Python :: 3
Classifier: License :: OSI Approved :: MIT License
Classifier: Operating System :: OS Independent
Requires-Python: >=3.6
License-File: LICENSE
Requires-Dist: requests
Requires-Dist: web3
Requires-Dist: eth-typing
Requires-Dist: eth-utils
Requires-Dist: eth-account
Requires-Dist: eth-rlp
